universal_transfer_operator/__init__.py
universal_transfer_operator-0.0.1a1.dist-info/entry_points.txt
universal_transfer_operator-0.0.1a1.dist-info/WHEEL
universal_transfer_operator-0.0.1a1.dist-info/METADATA
universal_transfer_operator-0.0.1a1.dist-info/RECORD
